[{"id":1,"first_name":"Cosmo","last_name":"Lown","email":"clown0@dot.gov","gender":"Non-binary"},
{"id":2,"first_name":"Ebba","last_name":"Bartke","email":"ebartke1@netscape.com","gender":"Genderfluid"},
{"id":3,"first_name":"Bryanty","last_name":"Scini","email":"bscini2@cpanel.net","gender":"Genderfluid"},
{"id":4,"first_name":"Nollie","last_name":"Patkin","email":"npatkin3@wufoo.com","gender":"Agender"},
{"id":5,"first_name":"Holt","last_name":"Ayer","email":"hayer4@cpanel.net","gender":"Male"},
{"id":6,"first_name":"Clerkclaude","last_name":"Landsman","email":"clandsman5@epa.gov","gender":"Polygender"},
{"id":7,"first_name":"Augusta","last_name":"Wollard","email":"awollard6@addtoany.com","gender":"Genderfluid"},
{"id":8,"first_name":"Barny","last_name":"Laugherane","email":"blaugherane7@va.gov","gender":"Genderqueer"},
{"id":9,"first_name":"Julieta","last_name":"La Wille","email":"jlawille8@com.com","gender":"Polygender"},
{"id":10,"first_name":"Dorene","last_name":"Wyne","email":"dwyne9@earthlink.net","gender":"Bigender"}]